winter/__init__.py
winter/_utils.py
winter/authentication.py
winter/common/__init__.py
winter/common/dao.py
winter/common/decorators.py
winter/common/exception.py
winter/common/ordering.py
winter/common/pagination.py
winter/common/schema.py
winter/core/__init__.py
winter/core/depends.py
winter/core/register/__init__.py
winter/core/register/auth.py
winter/core/register/exception.py
winter/core/register/logger.py
winter/core/register/mysql.py
winter/core/register/nacos.py
winter/winter.py
winter_cloud-0.1.48.dist-info/METADATA
winter_cloud-0.1.48.dist-info/WHEEL
winter_cloud-0.1.48.dist-info/RECORD
